setup.cfg
setup.py
bin/env2config
env2config/__init__.py
env2config/cli.py
env2config/conversions.py
env2config/interface.py
env2config/main.py
env2config/processors.py
env2config/util.py
env2config.egg-info/PKG-INFO
env2config.egg-info/SOURCES.txt
env2config.egg-info/dependency_links.txt
env2config.egg-info/requires.txt
env2config.egg-info/top_level.txt
env2config/services/__init__.py
env2config/services/hadoop.py
env2config/services/kafka.py
env2config/services/redis.py