Metadata-Version: 1.0
Name: env2config
Version: 0.6.1
Summary: Generate config files from environment variables
Home-page: https://github/dacjames/env2config
Author: Daniel Collins
Author-email: peterldowns@gmail.com
License: UNKNOWN
Platform: UNKNOWN
